cyberfusion/ClusterApiCli/__init__.py
cyberfusion/ClusterApiCli/_authenticators.py
cyberfusion/ClusterApiCli/_calls.py
cyberfusion/ClusterApiCli/_constants.py
cyberfusion/ClusterApiCli/_interfaces.py
cyberfusion/ClusterApiCli/api_user_info.py
cyberfusion/ClusterApiCli/exceptions.py
python3_cyberfusion_cluster_apicli-3.1.dist-info/METADATA
python3_cyberfusion_cluster_apicli-3.1.dist-info/WHEEL
python3_cyberfusion_cluster_apicli-3.1.dist-info/top_level.txt
python3_cyberfusion_cluster_apicli-3.1.dist-info/RECORD
