Metadata-Version: 2.1
Name: python3-cyberfusion-cluster-apicli
Version: 3.1
Summary: API client for Core API.
Author-email: Cyberfusion <support@cyberfusion.io>
Project-URL: Source, https://vcs.cyberfusion.nl/core/python3-cyberfusion-cluster-apicli
Requires-Dist: python3-cyberfusion-common ~=2.0
Requires-Dist: cached-property ==1.5.2
Requires-Dist: certifi ==2022.9.24
Requires-Dist: requests ==2.28.1
